<?xml version="1.0" encoding="UTF-8"?><record_update sys_domain="global" table="sn_decision_table_decision_condition">
    <sn_decision_table_decision_condition action="DELETE">
        <decision_input display_value="u_type">a6d52f670fef76902e576dd530d1b2b2</decision_input>
        <decision_table display_value="flow_and_script_decision_testv1 delta">26d56b670fef76902e576dd530d1b2fe</decision_table>
        <default_operator>=</default_operator>
        <description>スクリプトかフローか</description>
        <field/>
        <field_label/>
        <field_parent_table/>
        <label>u_type</label>
        <order>100</order>
        <parent display_value="">a900eed20f6ffa502e576dd530d1b2ef</parent>
        <reference/>
        <sys_class_name>sn_decision_table_decision_condition</sys_class_name>
        <sys_created_by>admin</sys_created_by>
        <sys_created_on>2026-03-17 06:23:56</sys_created_on>
        <sys_domain>global</sys_domain>
        <sys_id>63d5af670fef76902e576dd530d1b261</sys_id>
        <sys_mod_count>0</sys_mod_count>
        <sys_name/>
        <sys_package display_value="test" source="x_846092_test">9971d5aa0f9372102e576dd530d1b235</sys_package>
        <sys_policy/>
        <sys_scope display_value="test">9971d5aa0f9372102e576dd530d1b235</sys_scope>
        <sys_update_name>sn_decision_table_decision_condition_63d5af670fef76902e576dd530d1b261</sys_update_name>
        <sys_updated_by>admin</sys_updated_by>
        <sys_updated_on>2026-03-17 06:23:56</sys_updated_on>
        <type display_value="String">747127c1bf3320001875647fcf0739e0</type>
    </sn_decision_table_decision_condition>
    <sys_update_version action="INSERT_OR_UPDATE">
        <action>DELETE</action>
        <application display_value="test">9971d5aa0f9372102e576dd530d1b235</application>
        <file_path/>
        <instance_id>b0e25b9e3bdf7e14986d048aa4e45a4c</instance_id>
        <instance_name>dev364288</instance_name>
        <name>sn_decision_table_decision_condition_63d5af670fef76902e576dd530d1b261</name>
        <payload><![CDATA[<?xml version="1.0" encoding="UTF-8"?><record_update sys_domain="global" table="sn_decision_table_decision_condition"><sn_decision_table_decision_condition action="INSERT_OR_UPDATE"><decision_input display_value="u_type">a6d52f670fef76902e576dd530d1b2b2</decision_input><decision_table display_value="flow_and_script_decision_testv1 delta">26d56b670fef76902e576dd530d1b2fe</decision_table><default_operator>=</default_operator><description>スクリプトかフローか</description><field/><field_label/><field_parent_table/><label>u_type</label><order>100</order><parent display_value="">a900eed20f6ffa502e576dd530d1b2ef</parent><reference/><sys_class_name>sn_decision_table_decision_condition</sys_class_name><sys_created_by>admin</sys_created_by><sys_created_on>2026-03-17 06:23:56</sys_created_on><sys_domain>global</sys_domain><sys_id>63d5af670fef76902e576dd530d1b261</sys_id><sys_mod_count>0</sys_mod_count><sys_name/><sys_package display_value="test" source="x_846092_test">9971d5aa0f9372102e576dd530d1b235</sys_package><sys_policy/><sys_scope display_value="test">9971d5aa0f9372102e576dd530d1b235</sys_scope><sys_update_name>sn_decision_table_decision_condition_63d5af670fef76902e576dd530d1b261</sys_update_name><sys_updated_by>admin</sys_updated_by><sys_updated_on>2026-03-17 06:23:56</sys_updated_on><type display_value="String">747127c1bf3320001875647fcf0739e0</type></sn_decision_table_decision_condition></record_update>]]></payload>
        <payload_hash>1547823522</payload_hash>
        <record_name/>
        <reverted_from/>
        <source>f1f1e3cc0fabba102e576dd530d1b2be</source>
        <source_table>sys_update_set</source_table>
        <state>previous</state>
        <sys_created_by>admin</sys_created_by>
        <sys_created_on>2026-03-17 06:23:56</sys_created_on>
        <sys_id>27d5af670fef76902e576dd530d1b273</sys_id>
        <sys_mod_count>0</sys_mod_count>
        <sys_recorded_at>19cfa771da80000001</sys_recorded_at>
        <sys_updated_by>admin</sys_updated_by>
        <sys_updated_on>2026-03-17 06:23:56</sys_updated_on>
        <type>Decision Condition</type>
        <update_guid>e3d5af6785ef76902fee0f3121cd6f72</update_guid>
        <update_guid_history>e3d5af6785ef76902fee0f3121cd6f72:1547823522</update_guid_history>
    </sys_update_version>
    <sys_metadata_delete action="INSERT_OR_UPDATE">
        <sys_audit_delete display_value="">63466fa70fef76902e576dd530d1b296</sys_audit_delete>
        <sys_class_name>sys_metadata_delete</sys_class_name>
        <sys_created_by>admin</sys_created_by>
        <sys_created_on>2026-03-17 06:25:51</sys_created_on>
        <sys_db_object display_value="" name="sn_decision_table_decision_condition">sn_decision_table_decision_condition</sys_db_object>
        <sys_id>d530e0c1b76841028f27ff2d24770b89</sys_id>
        <sys_metadata>63d5af670fef76902e576dd530d1b261</sys_metadata>
        <sys_mod_count>0</sys_mod_count>
        <sys_name/>
        <sys_package display_value="test" source="x_846092_test">9971d5aa0f9372102e576dd530d1b235</sys_package>
        <sys_parent/>
        <sys_policy/>
        <sys_scope display_value="test">9971d5aa0f9372102e576dd530d1b235</sys_scope>
        <sys_scope_delete display_value="">41f55643b9304baa94ae148183eeee04</sys_scope_delete>
        <sys_update_name>sn_decision_table_decision_condition_63d5af670fef76902e576dd530d1b261</sys_update_name>
        <sys_update_version display_value="sn_decision_table_decision_condition_63d5af670fef76902e576dd530d1b261">27d5af670fef76902e576dd530d1b273</sys_update_version>
        <sys_updated_by>admin</sys_updated_by>
        <sys_updated_on>2026-03-17 06:25:51</sys_updated_on>
    </sys_metadata_delete>
</record_update>
